<?xml version="1.0" encoding="utf-8" ?>
<dwsync>
<file name="makepage.php" server="uasocial.com/public_html/" local="129678538309517076" remote="129678502200000000" />
<file name="NewPage.php" server="uasocial.com/public_html/" local="129678550200000000" remote="129678550200000000" />
<file name="pagewload.php" server="uasocial.com/public_html/" local="129681457455123879" remote="129681421200000000" />
<file name="pagepictures.php" server="uasocial.com/public_html/" local="129676020000000000" remote="129676020000000000" />
<file name="pagesettings.php" server="uasocial.com/public_html/" local="129678657730478959" remote="129678621600000000" />
<file name="makeadmin.php" server="uasocial.com/public_html/" local="129674164839056251" remote="129674128800000000" />
<file name="pagecontacts.php" server="uasocial.com/public_html/" local="129677697000000000" remote="129677697000000000" />
<file name="search.php" server="uasocial.com/public_html/" local="129674221170833141" remote="129674188800000000" />
<file name="index.php" server="uasocial.com/public_html/" local="129681456721275332" remote="129681420600000000" />
<file name="pagead.php" server="uasocial.com/public_html/" local="129678656543591073" remote="129678620400000000" />
</dwsync>